bemserver_api/__init__.py
bemserver_api/database.py
bemserver_api/exceptions.py
bemserver_api/settings.py
bemserver_api/extensions/__init__.py
bemserver_api/extensions/authentication.py
bemserver_api/extensions/integrity_error.py
bemserver_api/extensions/ma_fields.py
bemserver_api/extensions/smorest.py
bemserver_api/extensions/timezones.json
bemserver_api/resources/__init__.py
bemserver_api/resources/about/__init__.py
bemserver_api/resources/about/routes.py
bemserver_api/resources/about/schemas.py
bemserver_api/resources/analysis/__init__.py
bemserver_api/resources/analysis/completeness/__init__.py
bemserver_api/resources/analysis/completeness/routes.py
bemserver_api/resources/analysis/completeness/schemas.py
bemserver_api/resources/analysis/energy_consumption/__init__.py
bemserver_api/resources/analysis/energy_consumption/routes.py
bemserver_api/resources/analysis/energy_consumption/schemas.py
bemserver_api/resources/building_properties/__init__.py
bemserver_api/resources/building_properties/routes.py
bemserver_api/resources/building_properties/schemas.py
bemserver_api/resources/building_property_data/__init__.py
bemserver_api/resources/building_property_data/routes.py
bemserver_api/resources/building_property_data/schemas.py
bemserver_api/resources/buildings/__init__.py
bemserver_api/resources/buildings/routes.py
bemserver_api/resources/buildings/schemas.py
bemserver_api/resources/campaign_scopes/__init__.py
bemserver_api/resources/campaign_scopes/routes.py
bemserver_api/resources/campaign_scopes/schemas.py
bemserver_api/resources/campaigns/__init__.py
bemserver_api/resources/campaigns/routes.py
bemserver_api/resources/campaigns/schemas.py
bemserver_api/resources/energies/__init__.py
bemserver_api/resources/energies/routes.py
bemserver_api/resources/energies/schemas.py
bemserver_api/resources/energy_consumption_timeseries_by_buildings/__init__.py
bemserver_api/resources/energy_consumption_timeseries_by_buildings/routes.py
bemserver_api-0.26.0.dist-info/licenses/LICENSE
bemserver_api-0.26.0.dist-info/WHEEL
bemserver_api-0.26.0.dist-info/METADATA
bemserver_api-0.26.0.dist-info/RECORD
