Metadata-Version: 2.4
Name: bemserver-api
Version: 0.26.0
Summary: BEMServer API
Author-email: Jérôme Lafréchoux <jlafrechoux@nobatek.inef4.com>, David Frédérique <dfrederique@nobatek.inef4.com>
Maintainer-email: Jérôme Lafréchoux <jlafrechoux@nobatek.inef4.com>, David Frédérique <dfrederique@nobatek.inef4.com>
Requires-Python: >=3.9
Classifier: Development Status :: 4 - Beta
Classifier: Intended Audience :: Developers
Classifier: Topic :: Scientific/Engineering
Classifier: License :: OSI Approved :: MIT License
Classifier: Programming Language :: Python :: 3 :: Only
Classifier: Programming Language :: Python :: 3.9
Classifier: Programming Language :: Python :: 3.10
Classifier: Programming Language :: Python :: 3.11
Classifier: Programming Language :: Python :: 3.12
License-File: LICENSE
Requires-Dist: flask>=3.0.2,<4.0
Requires-Dist: python-dotenv>=1.0.0,<2.0
Requires-Dist: marshmallow>=3.18.0,<4.0
Requires-Dist: sqlalchemy>=2.0,<3.0
Requires-Dist: marshmallow-sqlalchemy>=1.1.1,<2.0
Requires-Dist: flask_smorest>=0.45.0,<0.46
Requires-Dist: apispec>=6.1.0,<7.0
Requires-Dist: authlib>=1.3.0,<2.0
Requires-Dist: bemserver-core>=0.21.0,<0.22
Project-URL: Issues, https://github.com/bemserver/bemserver-api/issues
Project-URL: Source, https://github.com/bemserver/bemserver-api
